nonebot_plugin_testhkk/__init__.py
nonebot_plugin_testhkk/ai_chat.py
nonebot_plugin_testhkk/config.py
nonebot_plugin_testhkk-0.1.0.dist-info/licenses/LICENSE
nonebot_plugin_testhkk-0.1.0.dist-info/METADATA
nonebot_plugin_testhkk-0.1.0.dist-info/WHEEL
nonebot_plugin_testhkk-0.1.0.dist-info/top_level.txt
nonebot_plugin_testhkk-0.1.0.dist-info/RECORD
