Metadata-Version: 2.4
Name: nonebot-plugin-testhkk
Version: 0.1.0
Summary: NoneBot2 插件，支持群聊 AI 调用
Author-email: Wohaokunr <Wohaokunr@gmail.com>
Project-URL: Repository, https://github.com/Wohaokunr/nonebot-plugin-testhkk
Requires-Python: <3.13,>=3.10
License-File: LICENSE
Requires-Dist: httpx<1.0.0,>=0.27.0
Requires-Dist: nonebot2<3.0.0,>=2.4.2
Requires-Dist: nonebot-plugin-uninfo<1.0.0,>=0.7.0
Requires-Dist: nonebot-plugin-alconna<1.0.0,>=0.56.2
Requires-Dist: nonebot-plugin-waiter<1.0.0,>=0.8.1
Requires-Dist: nonebot-plugin-localstore<1.0.0,>=0.7.4
Requires-Dist: nonebot-plugin-apscheduler<1.0.0,>=0.5.0
Requires-Dist: openai<2.0.0,>=1.12.0
Dynamic: license-file
